rich_progress/__init__.py
rich_progress/color_logger.py
rich_progress/progress_manager.py
rich_progress_manager-0.2.0.dist-info/LICENSE
rich_progress_manager-0.2.0.dist-info/METADATA
rich_progress_manager-0.2.0.dist-info/WHEEL
rich_progress_manager-0.2.0.dist-info/top_level.txt
rich_progress_manager-0.2.0.dist-info/RECORD
